{
  "id": "63e1c1ca-bbbb-8082-8007-b51393d05dc1",
  "name": "Pill Text Thai",
  "type": "text",
  "x": 866,
  "y": 652,
  "width": 33,
  "height": 17,
  "rotation": 0,
  "selrect": {
    "x": 866,
    "y": 652,
    "width": 33,
    "height": 17,
    "x1": 866,
    "y1": 652,
    "x2": 899,
    "y2": 669
  },
  "points": [
    {
      "x": 866,
      "y": 652
    },
    {
      "x": 899,
      "y": 652
    },
    {
      "x": 899,
      "y": 669
    },
    {
      "x": 866,
      "y": 669
    }
  ],
  "transform": {
    "a": 1.0,
    "b": 0.0,
    "c": 0.0,
    "d": 1.0,
    "e": 0.0,
    "f": 0.0
  },
  "transformInverse": {
    "a": 1.0,
    "b": 0.0,
    "c": 0.0,
    "d": 1.0,
    "e": 0.0,
    "f": 0.0
  },
  "parentId": "63e1c1ca-bbbb-8082-8007-b513935e730f",
  "frameId": "63e1c1ca-bbbb-8082-8007-b513935e730f",
  "flipX": null,
  "flipY": null,
  "growType": "auto-width",
  "content": {
    "type": "root",
    "children": [
      {
        "type": "paragraph-set",
        "children": [
          {
            "lineHeight": "1.2",
            "fontStyle": "normal",
            "children": [
              {
                "lineHeight": "1.2",
                "fontStyle": "normal",
                "textTransform": "none",
                "textAlign": "left",
                "fontId": "gfont-cascadia-mono",
                "fontSize": "14",
                "fontWeight": "400",
                "textDirection": "ltr",
                "fontVariantId": "regular",
                "textDecoration": "none",
                "letterSpacing": "0",
                "fills": [
                  {
                    "fillColor": "#203436",
                    "fillOpacity": 1
                  }
                ],
                "fontFamily": "Cascadia Mono",
                "text": "Thai"
              }
            ],
            "textTransform": "none",
            "textAlign": "left",
            "fontId": "gfont-cascadia-mono",
            "fontSize": "14",
            "fontWeight": "400",
            "textDirection": "ltr",
            "type": "paragraph",
            "fontVariantId": "regular",
            "textDecoration": "none",
            "letterSpacing": "0",
            "fills": [
              {
                "fillColor": "#203436",
                "fillOpacity": 1
              }
            ],
            "fontFamily": "Cascadia Mono"
          }
        ]
      }
    ]
  },
  "constraintsV": "top",
  "constraintsH": "left",
  "positionData": [
    {
      "x": 866,
      "y": 668,
      "width": 32.8125,
      "height": 16,
      "x1": 0,
      "y1": 0,
      "x2": 32.8125,
      "y2": 16,
      "fontStyle": "normal",
      "textTransform": "none",
      "fontSize": "14px",
      "fontWeight": "400",
      "textDecoration": "none",
      "letterSpacing": "normal",
      "fills": [
        {
          "fillColor": "#203436",
          "fillOpacity": 1
        }
      ],
      "direction": "ltr",
      "fontFamily": "\"Cascadia Mono\"",
      "text": "Thai"
    }
  ],
  "pageId": "63e1c1ca-bbbb-8082-8007-b51248ccbd17"
}