{
  "id": "3020c42d-f7eb-809c-8007-b03a79dc4b98",
  "name": "Pay Icon 1",
  "type": "rect",
  "x": 292,
  "y": 1180,
  "width": 40,
  "height": 28,
  "rotation": 0,
  "selrect": {
    "x": 292,
    "y": 1180,
    "width": 40,
    "height": 28,
    "x1": 292,
    "y1": 1180,
    "x2": 332,
    "y2": 1208
  },
  "points": [
    {
      "x": 292,
      "y": 1180
    },
    {
      "x": 332,
      "y": 1180
    },
    {
      "x": 332,
      "y": 1208
    },
    {
      "x": 292,
      "y": 1208
    }
  ],
  "transform": {
    "a": 1.0,
    "b": 0.0,
    "c": 0.0,
    "d": 1.0,
    "e": 0.0,
    "f": 0.0
  },
  "transformInverse": {
    "a": 1.0,
    "b": 0.0,
    "c": 0.0,
    "d": 1.0,
    "e": 0.0,
    "f": 0.0
  },
  "parentId": "3020c42d-f7eb-809c-8007-b03a7948cb3d",
  "frameId": "3020c42d-f7eb-809c-8007-b03a7948cb3d",
  "flipX": null,
  "flipY": null,
  "r2": 4,
  "proportionLock": false,
  "pageId": "3020c42d-f7eb-809c-8007-b039002853a1",
  "r3": 4,
  "constraintsV": "top",
  "constraintsH": "left",
  "r1": 4,
  "strokes": [],
  "proportion": 1,
  "r4": 4,
  "fills": [
    {
      "fillColor": "#e0e0e0",
      "fillOpacity": 1
    }
  ]
}