{
  "id": "63e1c1ca-bbbb-8082-8007-b51be16f8412",
  "name": "RevCard Tom K.",
  "type": "rect",
  "x": 32,
  "y": 2704,
  "width": 976,
  "height": 120,
  "rotation": 0,
  "selrect": {
    "x": 32,
    "y": 2704,
    "width": 976,
    "height": 120,
    "x1": 32,
    "y1": 2704,
    "x2": 1008,
    "y2": 2824
  },
  "points": [
    {
      "x": 32,
      "y": 2704
    },
    {
      "x": 1008,
      "y": 2704
    },
    {
      "x": 1008,
      "y": 2824
    },
    {
      "x": 32,
      "y": 2824
    }
  ],
  "transform": {
    "a": 1.0,
    "b": 0.0,
    "c": 0.0,
    "d": 1.0,
    "e": 0.0,
    "f": 0.0
  },
  "transformInverse": {
    "a": 1.0,
    "b": 0.0,
    "c": 0.0,
    "d": 1.0,
    "e": 0.0,
    "f": 0.0
  },
  "parentId": "63e1c1ca-bbbb-8082-8007-b51ba25098aa",
  "frameId": "63e1c1ca-bbbb-8082-8007-b51ba25098aa",
  "flipX": null,
  "flipY": null,
  "r2": 8,
  "proportionLock": false,
  "pageId": "63e1c1ca-bbbb-8082-8007-b51b1c45835a",
  "r3": 8,
  "constraintsV": "top",
  "constraintsH": "left",
  "r1": 8,
  "strokes": [
    {
      "strokeColor": "#e0e0e0",
      "strokeOpacity": 1,
      "strokeWidth": 1
    }
  ],
  "proportion": 1,
  "r4": 8,
  "fills": [
    {
      "fillColor": "#f9f9f9",
      "fillOpacity": 1
    }
  ]
}